rococo/__init__.py
rococo/auth/__init__.py
rococo/auth/tokens.py
rococo/config/__init__.py
rococo/config/config.py
rococo/data/__init__.py
rococo/data/base.py
rococo/data/dynamodb.py
rococo/data/mongodb.py
rococo/data/mysql.py
rococo/data/postgresql.py
rococo/data/surrealdb.py
rococo/emailing/__init__.py
rococo/emailing/base.py
rococo/emailing/config.py
rococo/emailing/enums.py
rococo/emailing/factory.py
rococo/emailing/mailjet.py
rococo/emailing/ses.py
rococo/faxing/__init__.py
rococo/faxing/base.py
rococo/faxing/config.py
rococo/faxing/enums.py
rococo/faxing/factory.py
rococo/faxing/ifax.py
rococo/messaging/__init__.py
rococo/messaging/base.py
rococo/messaging/rabbitmq.py
rococo/messaging/sqs.py
rococo/migrations/__init__.py
rococo/migrations/common/__init__.py
rococo/migrations/common/cli_base.py
rococo/migrations/common/migration_base.py
rococo/migrations/common/migration_runner.py
rococo/migrations/common/migration_template.py
rococo/migrations/mongo/__init__.py
rococo/migrations/mongo/cli.py
rococo/migrations/mongo/migration.py
rococo/migrations/mysql/__init__.py
rococo/migrations/mysql/cli.py
rococo/migrations/mysql/migration.py
rococo/migrations/postgres/__init__.py
rococo/migrations/postgres/cli.py
rococo/migrations/postgres/migration.py
rococo/models/__init__.py
rococo/models/email.py
rococo/models/login_method.py
rococo/models/organization.py
rococo/models/otp_method.py
rococo/models/person.py
rococo/models/person_organization_role.py
rococo/models/recovery_code.py
rococo/models/versioned_model.py
rococo/models/surrealdb/__init__.py
rococo/models/surrealdb/email.py
rococo/models/surrealdb/login_method.py
rococo/models/surrealdb/organization.py
rococo/models/surrealdb/otp_method.py
rococo/models/surrealdb/person.py
rococo/models/surrealdb/person_organization_role.py
rococo/models/surrealdb/surreal_versioned_model.py
rococo/plugins/__init__.py
rococo/plugins/pooled_connection.py
rococo/repositories/__init__.py
rococo/repositories/base_repository.py
rococo-1.2.1.dist-info/licenses/LICENSE
rococo-1.2.1.dist-info/METADATA
rococo-1.2.1.dist-info/WHEEL
rococo-1.2.1.dist-info/entry_points.txt
rococo-1.2.1.dist-info/top_level.txt
rococo-1.2.1.dist-info/RECORD
