Metadata-Version: 2.4
Name: rococo
Version: 1.2.1
Summary: A Python library to help build things the way we want them built
Home-page: https://github.com/EcorRouge/rococo
Author: Jay Grieves
Author-email: jaygrieves@gmail.com
License: MIT
Requires-Python: >=3.10
License-File: LICENSE
Requires-Dist: boto3>=1.28.55
Requires-Dist: python-dotenv<2.0,>=1.0.0
Provides-Extra: sms
Requires-Dist: twilio<10.0,>=9.8.6; extra == "sms"
Requires-Dist: jinja2<4.0,>=3.1.6; extra == "sms"
Provides-Extra: emailing
Requires-Dist: mailjet_rest<2.0,>=1.4.0; extra == "emailing"
Provides-Extra: messaging
Requires-Dist: pika<1.4,>=1.3.2; extra == "messaging"
Provides-Extra: faxing
Requires-Dist: requests<3.0,>=2.31.0; extra == "faxing"
Provides-Extra: data-common
Requires-Dist: DBUtils<4.0,>=3.1; extra == "data-common"
Provides-Extra: data-surreal
Requires-Dist: surrealdb<1.1,>=1.0.7; extra == "data-surreal"
Provides-Extra: data-mysql
Requires-Dist: PyMySQL<1.2,>=1.1.1; extra == "data-mysql"
Provides-Extra: data-mongo
Requires-Dist: PyMongo<5.0,>=4.6.3; extra == "data-mongo"
Provides-Extra: data-postgres
Requires-Dist: psycopg2-binary<3.0,>=2.9.10; extra == "data-postgres"
Provides-Extra: data-dynamodb
Requires-Dist: pynamodb<7.0,>=6.0.0; extra == "data-dynamodb"
Provides-Extra: data
Requires-Dist: DBUtils<4.0,>=3.1; extra == "data"
Requires-Dist: surrealdb<1.1,>=1.0.7; extra == "data"
Requires-Dist: PyMySQL<1.2,>=1.1.1; extra == "data"
Requires-Dist: PyMongo<5.0,>=4.6.3; extra == "data"
Requires-Dist: psycopg2-binary<3.0,>=2.9.10; extra == "data"
Requires-Dist: pynamodb<7.0,>=6.0.0; extra == "data"
Provides-Extra: all
Requires-Dist: DBUtils<4.0,>=3.1; extra == "all"
Requires-Dist: surrealdb<1.1,>=1.0.7; extra == "all"
Requires-Dist: PyMySQL<1.2,>=1.1.1; extra == "all"
Requires-Dist: PyMongo<5.0,>=4.6.3; extra == "all"
Requires-Dist: psycopg2-binary<3.0,>=2.9.10; extra == "all"
Requires-Dist: pynamodb<7.0,>=6.0.0; extra == "all"
Requires-Dist: mailjet_rest<2.0,>=1.4.0; extra == "all"
Requires-Dist: pika<1.4,>=1.3.2; extra == "all"
Requires-Dist: requests<3.0,>=2.31.0; extra == "all"
Requires-Dist: twilio<10.0,>=9.8.6; extra == "all"
Requires-Dist: jinja2<4.0,>=3.1.6; extra == "all"
Dynamic: author
Dynamic: author-email
Dynamic: description
Dynamic: description-content-type
Dynamic: home-page
Dynamic: license
Dynamic: license-file
Dynamic: provides-extra
Dynamic: requires-dist
Dynamic: requires-python
Dynamic: summary
